alef/bash/__init__.py
alef/cli/__init__.py
alef/cli/__main__.py
alef/logging/__init__.py
alef/logging/_impl.py
alef/shell/__init__.py
alef/shell/play.py
alef/shell/runner.py
alef/shell/wrap.py
alef/util/__init__.py
alef_namespace-0.2.0.dev2.dist-info/LICENSE
alef_namespace-0.2.0.dev2.dist-info/METADATA
alef_namespace-0.2.0.dev2.dist-info/WHEEL
alef_namespace-0.2.0.dev2.dist-info/top_level.txt
alef_namespace-0.2.0.dev2.dist-info/RECORD
